ufodiff/__init__.py
ufodiff/app.py
ufodiff/settings.py
ufodiff/subcommands/__init__.py
ufodiff/subcommands/delta.py
ufodiff/subcommands/diff.py
ufodiff/utilities/__init__.py
ufodiff/utilities/ufo.py
ufodiff-1.0.3.dist-info/LICENSE
ufodiff-1.0.3.dist-info/METADATA
ufodiff-1.0.3.dist-info/WHEEL
ufodiff-1.0.3.dist-info/entry_points.txt
ufodiff-1.0.3.dist-info/top_level.txt
ufodiff-1.0.3.dist-info/RECORD
